scotchcorner.py
scotchcorner-0.2.1.dist-info/METADATA
scotchcorner-0.2.1.dist-info/RECORD
scotchcorner-0.2.1.dist-info/WHEEL
scotchcorner-0.2.1.dist-info/top_level.txt
