Metadata-Version: 2.1
Name: scotchcorner
Version: 0.2.1
Summary: A different corner plot.
Home-page: https://github.com/mattpitkin/scotchcorner
Author: Matthew Pitkin
Author-email: matthew.pitkin@glasgow.ac.uk
License: UNKNOWN
Platform: UNKNOWN
Classifier: Development Status :: 4 - Beta
Classifier: License :: OSI Approved :: MIT License
Classifier: Intended Audience :: Science/Research
Classifier: Natural Language :: English
Classifier: Operating System :: OS Independent
Classifier: Programming Language :: Python
Classifier: Topic :: Scientific/Engineering :: Visualization
